ray_haystack/__about__.py
ray_haystack/__init__.py
ray_haystack/component_actor.py
ray_haystack/ray_pipeline.py
ray_haystack/ray_pipeline_events.py
ray_haystack/ray_pipeline_manager.py
ray_haystack/ray_pipeline_processor.py
ray_haystack/ray_pipeline_settings.py
ray_haystack/components/__init__.py
ray_haystack/components/in_memory_bm25_retriever.py
ray_haystack/components/in_memory_document_store.py
ray_haystack/components/in_memory_embedding_retriever.py
ray_haystack/graph/__init__.py
ray_haystack/graph/component_node.py
ray_haystack/graph/ray_pipeline_graph.py
ray_haystack/middleware/__init__.py
ray_haystack/middleware/delay_middleware.py
ray_haystack/middleware/middleware.py
ray_haystack/serialization/__init__.py
ray_haystack/serialization/component_wrapper.py
ray_haystack/serialization/generic_wrapper.py
ray_haystack/serialization/worker_asset.py
ray_haystack-0.1.0.dist-info/METADATA
ray_haystack-0.1.0.dist-info/WHEEL
ray_haystack-0.1.0.dist-info/licenses/LICENSE
ray_haystack-0.1.0.dist-info/RECORD
