Metadata-Version: 2.3
Name: ray-haystack
Version: 0.1.0
Summary: Haystack pipelines with Ray
Project-URL: Documentation, https://github.com/prosto/ray-haystack
Project-URL: Issues, https://github.com/prosto/ray-haystack/issues
Project-URL: Source, https://github.com/prosto/ray-haystack
Author-email: Sergey Bondarenco <sergey.bondarenco@outlook.com>
License-Expression: MIT
License-File: LICENSE
Keywords: AI,Haystack,RAG,Ray,semantic-search
Classifier: Development Status :: 4 - Beta
Classifier: Operating System :: OS Independent
Classifier: Programming Language :: Python
Classifier: Programming Language :: Python :: 3.8
Classifier: Programming Language :: Python :: 3.9
Classifier: Programming Language :: Python :: 3.10
Classifier: Programming Language :: Python :: Implementation :: CPython
Classifier: Programming Language :: Python :: Implementation :: PyPy
Requires-Python: >=3.8
Requires-Dist: haystack-ai
Requires-Dist: mergedeep
Requires-Dist: ray
Provides-Extra: all
Requires-Dist: black>=24.8.0; extra == 'all'
Requires-Dist: coverage[toml]>=6.5; extra == 'all'
Requires-Dist: git-changelog>=2.3; extra == 'all'
Requires-Dist: mypy>=1.11.2; extra == 'all'
Requires-Dist: pytest; extra == 'all'
Requires-Dist: ruff>=0.6.4; extra == 'all'
Provides-Extra: docs
Requires-Dist: black>=23.1.0; extra == 'docs'
Requires-Dist: mkdocs-coverage>=0.2; extra == 'docs'
Requires-Dist: mkdocs-material>=7.3; extra == 'docs'
Requires-Dist: mkdocs-section-index>=0.3; extra == 'docs'
Requires-Dist: mkdocs>=1.3; extra == 'docs'
Requires-Dist: mkdocstrings[python]; extra == 'docs'
Provides-Extra: maintain
Requires-Dist: git-changelog>=2.3; extra == 'maintain'
Provides-Extra: quality
Requires-Dist: black>=24.8.0; extra == 'quality'
Requires-Dist: ruff>=0.6.4; extra == 'quality'
Provides-Extra: tests
Requires-Dist: coverage[toml]>=6.5; extra == 'tests'
Requires-Dist: pytest; extra == 'tests'
Provides-Extra: typing
Requires-Dist: mypy>=1.11.2; extra == 'typing'
